{
    "host": "localhost",
    "port": "6000",
    "endpoints": [
        {
            "name": "search",
            "endpoint": "/search",
            "method": "GET",
            "contentType": "application/json",
            "params": {
                "url": [
                    "name"
                ],
                "PLCH": []
            }
        },
        {
            "name": "getEntries",
            "endpoint": "/todo-list/PLCH_ID/entries",
            "method": "GET",
            "contentType": "application/json",
            "params": {
                "url": [

                ],
                "PLCH": [
                    {
                        "plch": "PLCH_ID",
                        "attr": "listId"
                    }
                ]
            }
        }
    ]
}